edmt/__init__.py
edmt/analysis/__init__.py
edmt/analysis/analysis.py
edmt/base/__init__.py
edmt/base/base.py
edmt/contrib/__init__.py
edmt/contrib/utils.py
edmt/conversion/__init__.py
edmt/conversion/computational.py
edmt/conversion/conversion.py
edmt/mapping/__init__.py
edmt/mapping/mapping.py
edmt/mapping/maps.py
edmt/models/__init__.py
edmt/models/airtable.py
edmt/models/drones.py
edmt/plotting/__init__.py
edmt-1.0.1.dist-info/licenses/LICENSE
edmt-1.0.1.dist-info/METADATA
edmt-1.0.1.dist-info/WHEEL
edmt-1.0.1.dist-info/entry_points.txt
edmt-1.0.1.dist-info/top_level.txt
edmt-1.0.1.dist-info/RECORD
