Metadata-Version: 2.4
Name: edmt
Version: 1.0.1
Summary: Environmental Data Management Toolbox
Author-email: "Odero, Kuloba & musasia" <franodex10@gmail.com>
License-Expression: MIT
Project-URL: Homepage, https://github.com/envqwewdmt/EDMT
Classifier: Programming Language :: Python :: 3
Classifier: Operating System :: OS Independent
Requires-Python: >=3.9
License-File: LICENSE
Requires-Dist: contextily>=1.4.0
Requires-Dist: contourpy>=1.2.1
Requires-Dist: fiona==1.9.6
Requires-Dist: folium>=0.18.0
Requires-Dist: geopandas>=0.12.2
Requires-Dist: mapclassify>=2.8.0
Requires-Dist: plotly>=5.24.1
Requires-Dist: seaborn>=0.13.2
Requires-Dist: tqdm>=4
Requires-Dist: pillow>=11.3.0
Dynamic: license-file
